progressive_overload/__init__.py
progressive_overload/__main__.py
progressive_overload/cli.py
progressive_overload/guessing.py
progressive_overload/progressive_overload.py
progressive_overload-0.2.1.dist-info/METADATA
progressive_overload-0.2.1.dist-info/RECORD
progressive_overload-0.2.1.dist-info/WHEEL
progressive_overload-0.2.1.dist-info/entry_points.txt
progressive_overload-0.2.1.dist-info/top_level.txt
tests/__init__.py
tests/test_examples.py
tests/test_guessing.py
tests/test_invalid.py
