Metadata-Version: 2.1
Name: progressive-overload
Version: 0.2.1
Summary: Calculates the next workout sets for progressive overload given previous ones.
Home-page: https://github.com/thomasleese/progressive-overload
Author: Thomas Leese
Author-email: thomas@leese.io
License: UNKNOWN
Platform: UNKNOWN
Classifier: Programming Language :: Python :: 3
Classifier: License :: OSI Approved :: MIT License
Classifier: Operating System :: OS Independent
Requires-Dist: PyYaml
